d6dice/__init__.py
d6dice/__main__.py
d6dice/console.py
d6dice/dice.py
d6dice/main.py
d6dice/test/__init__.py
d6dice/test/test_d6Dice.py
d6dice-0.2.2.dist-info/entry_points.txt
d6dice-0.2.2.dist-info/LICENSE
d6dice-0.2.2.dist-info/WHEEL
d6dice-0.2.2.dist-info/METADATA
d6dice-0.2.2.dist-info/RECORD
